audio/__init__.py
audio/_core.py
audio/lsb.py
image/__init__.py
image/_core.py
image/alpha.py
image/color.py
image/combo.py
image/lsb.py
image/region.py
stegopy-0.1.0.dist-info/licenses/LICENSE
stegopy-0.1.0.dist-info/METADATA
stegopy-0.1.0.dist-info/WHEEL
stegopy-0.1.0.dist-info/entry_points.txt
stegopy-0.1.0.dist-info/top_level.txt
stegopy-0.1.0.dist-info/RECORD
