Metadata-Version: 2.4
Name: stegopy
Version: 0.1.0
Summary: A deterministic, no-magic Python toolkit for hiding messages in media. Built with hyperfixation.
Home-page: https://github.com/JeremyDeveloper/stegopy
Author: JeremyDeveloper
License: MIT
Project-URL: Homepage, https://github.com/JeremyDeveloper/stegopy
Project-URL: Repository, https://github.com/JeremyDeveloper/stegopy
Project-URL: Issues, https://github.com/JeremyDeveloper/stegopy/issues
Keywords: steganography,image processing,audio processing,lsb,stego,data hiding
Classifier: Programming Language :: Python :: 3
Classifier: License :: OSI Approved :: MIT License
Classifier: Operating System :: OS Independent
Requires-Python: >=3.7
License-File: LICENSE
Requires-Dist: Pillow>=11.2.1
Dynamic: home-page
Dynamic: license-file
Dynamic: requires-python
